<?xml version="1.0" encoding="UTF-8"?>
<?Siebel-Property-Set EscapeNames="false"?>
<definitions xmlns="http://schemas.xmlsoap.org/wsdl/" xmlns:soap="http://schemas.xmlsoap.org/wsdl/soap/" xmlns:xsdLocal1="urn:/crmondemand/xml/Territory/Data" targetNamespace="urn:crmondemand/ws/ecbs/territory/" xmlns:soapenc="http://schemas.xmlsoap.org/soap/encoding/" xmlns:xsdLocal2="urn:/crmondemand/xml/Territory/Query" xmlns:xsd="http://www.w3.org/2001/XMLSchema" xmlns:tns="urn:crmondemand/ws/ecbs/territory/"><types><xsd:schema elementFormDefault="qualified" attributeFormDefault="unqualified" targetNamespace="urn:/crmondemand/xml/Territory/Query" xmlns:xsdLocal2="urn:/crmondemand/xml/Territory/Query" xmlns:xsd="http://www.w3.org/2001/XMLSchema"><xsd:annotation><xsd:documentation>Copyright (C) 2001, 2008, Oracle and/or its affiliates. All rights reserved. Siebel XSD Generation</xsd:documentation></xsd:annotation><xsd:element name="ListOfTerritory" type="xsdLocal2:ListOfTerritoryQuery"></xsd:element><xsd:complexType name="ListOfTerritoryTopElmtQuery"><xsd:sequence><xsd:element name="ListOfTerritory" maxOccurs="1" minOccurs="0" type="xsdLocal2:ListOfTerritoryQuery"></xsd:element></xsd:sequence></xsd:complexType><xsd:complexType name="ListOfTerritoryQuery"><xsd:sequence><xsd:element name="Territory" maxOccurs="1" minOccurs="0" type="xsdLocal2:TerritoryQuery"></xsd:element></xsd:sequence><xsd:attribute name="pagesize" type="xsd:integer"></xsd:attribute><xsd:attribute name="startrownum" type="xsd:integer"></xsd:attribute><xsd:attribute name="recordcountneeded" type="xsd:boolean"></xsd:attribute></xsd:complexType><xsd:complexType name="TerritoryQuery"><xsd:all><xsd:element name="ModifiedDate" maxOccurs="1" minOccurs="0" type="xsdLocal2:queryType"></xsd:element><xsd:element name="CreatedDate" maxOccurs="1" minOccurs="0" type="xsdLocal2:queryType"></xsd:element><xsd:element name="ModifiedById" maxOccurs="1" minOccurs="0" type="xsdLocal2:queryType"></xsd:element><xsd:element name="CreatedById" maxOccurs="1" minOccurs="0" type="xsdLocal2:queryType"></xsd:element><xsd:element name="ModId" maxOccurs="1" minOccurs="0" type="xsdLocal2:queryType"></xsd:element><xsd:element name="Id" maxOccurs="1" minOccurs="0" type="xsdLocal2:queryType"></xsd:element><xsd:element name="CreatedBy" maxOccurs="1" minOccurs="0" type="xsdLocal2:queryType"></xsd:element><xsd:element name="ParentTerritoryExternalSystemId" maxOccurs="1" minOccurs="0" type="xsdLocal2:queryType"></xsd:element><xsd:element name="CurrencyCode" maxOccurs="1" minOccurs="0" type="xsdLocal2:queryType"></xsd:element><xsd:element name="Description" maxOccurs="1" minOccurs="0" type="xsdLocal2:queryType"></xsd:element><xsd:element name="TerritoryName" maxOccurs="1" minOccurs="0" type="xsdLocal2:queryType"></xsd:element><xsd:element name="CurrentQuota" maxOccurs="1" minOccurs="0" type="xsdLocal2:queryType"></xsd:element><xsd:element name="ParentTerritoryId" maxOccurs="1" minOccurs="0" type="xsdLocal2:queryType"></xsd:element><xsd:element name="ParentTerritoryName" maxOccurs="1" minOccurs="0" type="xsdLocal2:queryType"></xsd:element><xsd:element name="ExternalSystemId" maxOccurs="1" minOccurs="0" type="xsdLocal2:queryType"></xsd:element><xsd:element name="UpdatedByAlias" maxOccurs="1" minOccurs="0" type="xsdLocal2:queryType"></xsd:element><xsd:element name="UpdatedByEMailAddr" maxOccurs="1" minOccurs="0" type="xsdLocal2:queryType"></xsd:element><xsd:element name="UpdatedByExternalSystemId" maxOccurs="1" minOccurs="0" type="xsdLocal2:queryType"></xsd:element><xsd:element name="UpdatedByFirstName" maxOccurs="1" minOccurs="0" type="xsdLocal2:queryType"></xsd:element><xsd:element name="UpdatedByFullName" maxOccurs="1" minOccurs="0" type="xsdLocal2:queryType"></xsd:element><xsd:element name="UpdatedByIntegrationId" maxOccurs="1" minOccurs="0" type="xsdLocal2:queryType"></xsd:element><xsd:element name="UpdatedByLastName" maxOccurs="1" minOccurs="0" type="xsdLocal2:queryType"></xsd:element><xsd:element name="UpdatedByUserSignInId" maxOccurs="1" minOccurs="0" type="xsdLocal2:queryType"></xsd:element><xsd:element name="CreatedByAlias" maxOccurs="1" minOccurs="0" type="xsdLocal2:queryType"></xsd:element><xsd:element name="CreatedByEMailAddr" maxOccurs="1" minOccurs="0" type="xsdLocal2:queryType"></xsd:element><xsd:element name="CreatedByExternalSystemId" maxOccurs="1" minOccurs="0" type="xsdLocal2:queryType"></xsd:element><xsd:element name="CreatedByFirstName" maxOccurs="1" minOccurs="0" type="xsdLocal2:queryType"></xsd:element><xsd:element name="CreatedByFullName" maxOccurs="1" minOccurs="0" type="xsdLocal2:queryType"></xsd:element><xsd:element name="CreatedByIntegrationId" maxOccurs="1" minOccurs="0" type="xsdLocal2:queryType"></xsd:element><xsd:element name="CreatedByLastName" maxOccurs="1" minOccurs="0" type="xsdLocal2:queryType"></xsd:element><xsd:element name="CreatedByUserSignInId" maxOccurs="1" minOccurs="0" type="xsdLocal2:queryType"></xsd:element><xsd:element name="ModifiedBy" maxOccurs="1" minOccurs="0" type="xsdLocal2:queryType"></xsd:element></xsd:all><xsd:attribute name="searchspec" type="xsd:string"></xsd:attribute></xsd:complexType><xsd:complexType name="queryType"><xsd:simpleContent><xsd:extension base="xsd:string"><xsd:attribute name="sortorder" type="xsd:string"></xsd:attribute><xsd:attribute name="sortsequence" type="xsd:string"></xsd:attribute></xsd:extension></xsd:simpleContent></xsd:complexType></xsd:schema><xsd:schema elementFormDefault="qualified" attributeFormDefault="unqualified" targetNamespace="urn:crmondemand/ws/ecbs/territory/" xmlns:xsd="http://www.w3.org/2001/XMLSchema"><xsd:import namespace="urn:/crmondemand/xml/Territory/Query"></xsd:import><xsd:import namespace="urn:/crmondemand/xml/Territory/Data"></xsd:import><xsd:element name="TerritoryInsert_Input"><xsd:complexType><xsd:sequence><xsd:element ref="xsdLocal1:ListOfTerritory"></xsd:element><xsd:element name="LOVLanguageMode" minOccurs="0" type="xsd:string"></xsd:element><xsd:element name="ViewMode" minOccurs="0" type="xsd:string"></xsd:element><xsd:element name="Echo" minOccurs="0" type="xsd:string"></xsd:element></xsd:sequence></xsd:complexType></xsd:element><xsd:element name="TerritoryInsert_Output"><xsd:complexType><xsd:sequence><xsd:element ref="xsdLocal1:ListOfTerritory"></xsd:element></xsd:sequence></xsd:complexType></xsd:element><xsd:element name="TerritoryQueryPage_Input"><xsd:complexType><xsd:sequence><xsd:element ref="xsdLocal2:ListOfTerritory"></xsd:element><xsd:element name="LOVLanguageMode" minOccurs="0" type="xsd:string"></xsd:element><xsd:element name="ViewMode" minOccurs="0" type="xsd:string"></xsd:element></xsd:sequence></xsd:complexType></xsd:element><xsd:element name="TerritoryQueryPage_Output"><xsd:complexType><xsd:sequence><xsd:element ref="xsdLocal1:ListOfTerritory"></xsd:element></xsd:sequence></xsd:complexType></xsd:element><xsd:element name="TerritoryUpdate_Input"><xsd:complexType><xsd:sequence><xsd:element ref="xsdLocal1:ListOfTerritory"></xsd:element><xsd:element name="LOVLanguageMode" minOccurs="0" type="xsd:string"></xsd:element><xsd:element name="ViewMode" minOccurs="0" type="xsd:string"></xsd:element><xsd:element name="Echo" minOccurs="0" type="xsd:string"></xsd:element></xsd:sequence></xsd:complexType></xsd:element><xsd:element name="TerritoryUpdate_Output"><xsd:complexType><xsd:sequence><xsd:element ref="xsdLocal1:ListOfTerritory"></xsd:element></xsd:sequence></xsd:complexType></xsd:element><xsd:element name="TerritoryDelete_Input"><xsd:complexType><xsd:sequence><xsd:element ref="xsdLocal1:ListOfTerritory"></xsd:element><xsd:element name="LOVLanguageMode" minOccurs="0" type="xsd:string"></xsd:element><xsd:element name="ViewMode" minOccurs="0" type="xsd:string"></xsd:element><xsd:element name="Echo" minOccurs="0" type="xsd:string"></xsd:element></xsd:sequence></xsd:complexType></xsd:element><xsd:element name="TerritoryDelete_Output"><xsd:complexType><xsd:sequence><xsd:element ref="xsdLocal1:ListOfTerritory"></xsd:element></xsd:sequence></xsd:complexType></xsd:element><xsd:element name="TerritoryExecute_Input"><xsd:complexType><xsd:sequence><xsd:element ref="xsdLocal1:ListOfTerritory"></xsd:element><xsd:element name="LOVLanguageMode" minOccurs="0" type="xsd:string"></xsd:element><xsd:element name="ViewMode" minOccurs="0" type="xsd:string"></xsd:element><xsd:element name="Echo" minOccurs="0" type="xsd:string"></xsd:element></xsd:sequence></xsd:complexType></xsd:element><xsd:element name="TerritoryExecute_Output"><xsd:complexType><xsd:sequence><xsd:element ref="xsdLocal1:ListOfTerritory"></xsd:element></xsd:sequence></xsd:complexType></xsd:element></xsd:schema><xsd:schema elementFormDefault="qualified" attributeFormDefault="unqualified" xmlns:xsdLocal1="urn:/crmondemand/xml/Territory/Data" targetNamespace="urn:/crmondemand/xml/Territory/Data" xmlns:xsd="http://www.w3.org/2001/XMLSchema"><xsd:annotation><xsd:documentation>Copyright (C) 2001, 2008, Oracle and/or its affiliates. All rights reserved. Siebel XSD Generation</xsd:documentation></xsd:annotation><xsd:element name="ListOfTerritory" type="xsdLocal1:ListOfTerritoryData"></xsd:element><xsd:complexType name="ListOfTerritoryTopElmtData"><xsd:sequence><xsd:element name="ListOfTerritory" maxOccurs="1" minOccurs="1" type="xsdLocal1:ListOfTerritoryData"></xsd:element></xsd:sequence></xsd:complexType><xsd:complexType name="ListOfTerritoryData"><xsd:sequence><xsd:element name="Territory" maxOccurs="unbounded" minOccurs="0" type="xsdLocal1:TerritoryData"></xsd:element></xsd:sequence><xsd:attribute name="lastpage" type="xsd:boolean"></xsd:attribute><xsd:attribute name="recordcount" type="xsd:integer"></xsd:attribute></xsd:complexType><xsd:complexType name="TerritoryData"><xsd:all><xsd:element name="ModifiedDate" maxOccurs="1" minOccurs="0" type="xsd:dateTime"></xsd:element><xsd:element name="CreatedDate" maxOccurs="1" minOccurs="0" type="xsd:dateTime"></xsd:element><xsd:element name="ModifiedById" maxOccurs="1" minOccurs="0" type="xsd:string"></xsd:element><xsd:element name="CreatedById" maxOccurs="1" minOccurs="0" type="xsd:string"></xsd:element><xsd:element name="ModId" maxOccurs="1" minOccurs="0" type="xsd:int"></xsd:element><xsd:element name="Id" maxOccurs="1" minOccurs="0" type="xsd:string"></xsd:element><xsd:element name="CreatedBy" maxOccurs="1" minOccurs="0" type="xsd:string"></xsd:element><xsd:element name="ParentTerritoryExternalSystemId" maxOccurs="1" minOccurs="0" type="xsd:string"></xsd:element><xsd:element name="CurrencyCode" maxOccurs="1" minOccurs="0" type="xsd:string"></xsd:element><xsd:element name="Description" maxOccurs="1" minOccurs="0" type="xsd:string"></xsd:element><xsd:element name="TerritoryName" maxOccurs="1" minOccurs="0" type="xsd:string"></xsd:element><xsd:element name="CurrentQuota" maxOccurs="1" minOccurs="0" type="xsd:decimal"></xsd:element><xsd:element name="ParentTerritoryId" maxOccurs="1" minOccurs="0" type="xsd:string"></xsd:element><xsd:element name="ParentTerritoryName" maxOccurs="1" minOccurs="0" type="xsd:string"></xsd:element><xsd:element name="ExternalSystemId" maxOccurs="1" minOccurs="0" type="xsd:string"></xsd:element><xsd:element name="UpdatedByAlias" maxOccurs="1" minOccurs="0" type="xsd:string"></xsd:element><xsd:element name="UpdatedByEMailAddr" maxOccurs="1" minOccurs="0" type="xsd:string"></xsd:element><xsd:element name="UpdatedByExternalSystemId" maxOccurs="1" minOccurs="0" type="xsd:string"></xsd:element><xsd:element name="UpdatedByFirstName" maxOccurs="1" minOccurs="0" type="xsd:string"></xsd:element><xsd:element name="UpdatedByFullName" maxOccurs="1" minOccurs="0" type="xsd:string"></xsd:element><xsd:element name="UpdatedByIntegrationId" maxOccurs="1" minOccurs="0" type="xsd:string"></xsd:element><xsd:element name="UpdatedByLastName" maxOccurs="1" minOccurs="0" type="xsd:string"></xsd:element><xsd:element name="UpdatedByUserSignInId" maxOccurs="1" minOccurs="0" type="xsd:string"></xsd:element><xsd:element name="CreatedByAlias" maxOccurs="1" minOccurs="0" type="xsd:string"></xsd:element><xsd:element name="CreatedByEMailAddr" maxOccurs="1" minOccurs="0" type="xsd:string"></xsd:element><xsd:element name="CreatedByExternalSystemId" maxOccurs="1" minOccurs="0" type="xsd:string"></xsd:element><xsd:element name="CreatedByFirstName" maxOccurs="1" minOccurs="0" type="xsd:string"></xsd:element><xsd:element name="CreatedByFullName" maxOccurs="1" minOccurs="0" type="xsd:string"></xsd:element><xsd:element name="CreatedByIntegrationId" maxOccurs="1" minOccurs="0" type="xsd:string"></xsd:element><xsd:element name="CreatedByLastName" maxOccurs="1" minOccurs="0" type="xsd:string"></xsd:element><xsd:element name="CreatedByUserSignInId" maxOccurs="1" minOccurs="0" type="xsd:string"></xsd:element><xsd:element name="ModifiedBy" maxOccurs="1" minOccurs="0" type="xsd:string"></xsd:element></xsd:all><xsd:attribute name="operation" type="xsd:string"></xsd:attribute></xsd:complexType></xsd:schema></types><message name="TerritoryInsert_Input"><part name="TerritoryInsert_Input" element="tns:TerritoryInsert_Input"></part></message><message name="TerritoryInsert_Output"><part name="TerritoryInsert_Output" element="tns:TerritoryInsert_Output"></part></message><message name="TerritoryQueryPage_Input"><part name="TerritoryQueryPage_Input" element="tns:TerritoryQueryPage_Input"></part></message><message name="TerritoryQueryPage_Output"><part name="TerritoryQueryPage_Output" element="tns:TerritoryQueryPage_Output"></part></message><message name="TerritoryUpdate_Input"><part name="TerritoryUpdate_Input" element="tns:TerritoryUpdate_Input"></part></message><message name="TerritoryUpdate_Output"><part name="TerritoryUpdate_Output" element="tns:TerritoryUpdate_Output"></part></message><message name="TerritoryDelete_Input"><part name="TerritoryDelete_Input" element="tns:TerritoryDelete_Input"></part></message><message name="TerritoryDelete_Output"><part name="TerritoryDelete_Output" element="tns:TerritoryDelete_Output"></part></message><message name="TerritoryExecute_Input"><part name="TerritoryExecute_Input" element="tns:TerritoryExecute_Input"></part></message><message name="TerritoryExecute_Output"><part name="TerritoryExecute_Output" element="tns:TerritoryExecute_Output"></part></message><portType name="Territory"><operation name="TerritoryInsert"><input message="tns:TerritoryInsert_Input"></input><output message="tns:TerritoryInsert_Output"></output></operation><operation name="TerritoryQueryPage"><input message="tns:TerritoryQueryPage_Input"></input><output message="tns:TerritoryQueryPage_Output"></output></operation><operation name="TerritoryUpdate"><input message="tns:TerritoryUpdate_Input"></input><output message="tns:TerritoryUpdate_Output"></output></operation><operation name="TerritoryDelete"><input message="tns:TerritoryDelete_Input"></input><output message="tns:TerritoryDelete_Output"></output></operation><operation name="TerritoryExecute"><input message="tns:TerritoryExecute_Input"></input><output message="tns:TerritoryExecute_Output"></output></operation></portType><binding name="Territory" type="tns:Territory"><soap:binding transport="http://schemas.xmlsoap.org/soap/http" style="document"></soap:binding><operation name="TerritoryInsert"><soap:operation soapAction="document/urn:crmondemand/ws/ecbs/territory/:TerritoryInsert"></soap:operation><input><soap:body use="literal"></soap:body></input><output><soap:body use="literal"></soap:body></output></operation><operation name="TerritoryQueryPage"><soap:operation soapAction="document/urn:crmondemand/ws/ecbs/territory/:TerritoryQueryPage"></soap:operation><input><soap:body use="literal"></soap:body></input><output><soap:body use="literal"></soap:body></output></operation><operation name="TerritoryUpdate"><soap:operation soapAction="document/urn:crmondemand/ws/ecbs/territory/:TerritoryUpdate"></soap:operation><input><soap:body use="literal"></soap:body></input><output><soap:body use="literal"></soap:body></output></operation><operation name="TerritoryDelete"><soap:operation soapAction="document/urn:crmondemand/ws/ecbs/territory/:TerritoryDelete"></soap:operation><input><soap:body use="literal"></soap:body></input><output><soap:body use="literal"></soap:body></output></operation><operation name="TerritoryExecute"><soap:operation soapAction="document/urn:crmondemand/ws/ecbs/territory/:TerritoryExecute"></soap:operation><input><soap:body use="literal"></soap:body></input><output><soap:body use="literal"></soap:body></output></operation></binding><service name="Territory"><port binding="tns:Territory" name="Territory"><soap:address location="https://secure-ausomxfba.crmondemand.com/Services/Integration"></soap:address></port></service></definitions>